<labels>
  <label label="[CZ] facies articularis sternalis" text="[CZ] pro incisura clavicularis sterni" priority="2" x="-1.653598523277427" y="3.798264124452549" z="142.37400932100877" x2="-3.3543104498179326" y2="7.581180834351426" z2="281.9560528408525" label_CZ="facies articularis sternalis" text_CZ="pro incisura clavicularis sterni"/>
  <label label="[CZ] extremitas sternalis" text="[CZ] lig. sternoclaviculare ant. et. post., lig. interclaviculare&#xD;&#xD;ZAČÍNÁ ZDE:&#xD;m. sternohyoideus" priority="2" x="11.966123931292996" y="10.151795391099029" z="125.59366092881824" x2="52.61431999922976" y2="-52.47324827434069" z2="226.3595021724753" label_CZ="extremitas sternalis" text_CZ="lig. sternoclaviculare ant. et. post., lig. interclaviculare&#xD;&#xD;ZAČÍNÁ ZDE:&#xD;m. sternohyoideus"/>
  <label label="[CZ] corpus claviculae" text="[CZ] ZAČÍNÁ ZDE:&#xD;m. sternocleidomastoideus, &#xD;m. pectoralis major (pars clavicularis)" priority="2" x="1.0736234620933032" y="-27.311573119826623" z="0.4380570244331912" x2="62.82058973599527" y2="-112.31320718987024" z2="26.203470751115702" label_CZ="corpus claviculae" text_CZ="ZAČÍNÁ ZDE:&#xD;m. sternocleidomastoideus, &#xD;m. pectoralis major (pars clavicularis)"/>
  <label label="[CZ] extremitas acromialis" text="[CZ] lig. acromioclaviculare&#xD;&#xD;ZAČÍNÁ ZDE:&#xD;m. deltoideus (pars clavicularis)&#xD;&#xD;UPÍNÁ SE ZDE:&#xD;m trapezius (pars descendens)" priority="2" x="-0.5699982812045025" y="-26.165705140267352" z="-129.3285719276165" x2="-1.190127777214426" y2="-45.278044302624885" z2="-227.4832148700224" label_CZ="extremitas acromialis" text_CZ="lig. acromioclaviculare&#xD;&#xD;ZAČÍNÁ ZDE:&#xD;m. deltoideus (pars clavicularis)&#xD;&#xD;UPÍNÁ SE ZDE:&#xD;m trapezius (pars descendens)"/>
  <label label="[CZ] facies articularis acromialis" text="[CZ] pro facies articularis clavicularis acromii" priority="2" x="-5.709260573535073" y="-9.126879840039477" z="-141.61744739679165" x2="-8.297861481378131" y2="123.8501786282035" z2="-289.49318333103116" label_CZ="facies articularis acromialis" text_CZ="pro facies articularis clavicularis acromii"/>
  <label label="[CZ] tuberculum conoideum" text="[CZ] spolu s linea trapezoidea tvoří tuberositas ligamenti coracoclavicularis&#xD;&#xD;ligamentum conoideum" priority="2" x="25.280552047476785" y="17.89161548704851" z="-73.52766001372963" x2="72.93040745352548" y2="50.469696394801716" z2="-132.0437754366934" label_CZ="tuberculum conoideum" text_CZ="spolu s linea trapezoidea tvoří tuberositas ligamenti coracoclavicularis&#xD;&#xD;ligamentum conoideum"/>
  <label label="[CZ] sulcus musculi subclavii" text="[CZ] UPÍNÁ SE ZDE:&#xD;m. subclavius" priority="2" x="8.261666528773311" y="0.690918816962319" z="-44.70623662155911" x2="-68.119711369717" y2="12.517872944668385" z2="-114.07186080232312" label_CZ="sulcus musculi subclavii" text_CZ="UPÍNÁ SE ZDE:&#xD;m. subclavius"/>
  <label label="[CZ] linea trapezoidea" text="[CZ] spolu s tuberculum conoideum tvoří tuberositas ligamenti coracoclavicularis&#xD;&#xD;lig. trapezoideum" priority="2" x="6.491549335997465" y="9.045532352452115" z="-112.30094182381008" x2="35.29063050952422" y2="38.77160894622711" z2="-156.02928551080652" label_CZ="linea trapezoidea" text_CZ="spolu s tuberculum conoideum tvoří tuberositas ligamenti coracoclavicularis&#xD;&#xD;lig. trapezoideum"/>
  <label label="[CZ] impressio ligamenti costoclavicularis" text="[CZ] lig. costoclaviculare" priority="2" x="-19.338523777949405" y="7.391509327046657" z="89.39359266457758" x2="-75.04359440982836" y2="15.19934422135799" z2="150.2120954405625" label_CZ="impressio ligamenti costoclavicularis" text_CZ="lig. costoclaviculare"/>
</labels>